{
  "ask_recipe": {
    "precision": 1.0,
    "recall": 1.0,
    "f1-score": 1.0,
    "support": 15,
    "confused_with": {}
  },
  "goodbye": {
    "precision": 1.0,
    "recall": 1.0,
    "f1-score": 1.0,
    "support": 10,
    "confused_with": {}
  },
  "ask_healthy_eating_examples": {
    "precision": 1.0,
    "recall": 1.0,
    "f1-score": 1.0,
    "support": 31,
    "confused_with": {}
  },
  "chitchat": {
    "precision": 1.0,
    "recall": 1.0,
    "f1-score": 1.0,
    "support": 3,
    "confused_with": {}
  },
  "ask_healthy_eating_basic": {
    "precision": 1.0,
    "recall": 1.0,
    "f1-score": 1.0,
    "support": 30,
    "confused_with": {}
  },
  "ask_for_a_joke": {
    "precision": 1.0,
    "recall": 1.0,
    "f1-score": 1.0,
    "support": 7,
    "confused_with": {}
  },
  "ask_for_help": {
    "precision": 1.0,
    "recall": 1.0,
    "f1-score": 1.0,
    "support": 19,
    "confused_with": {}
  },
  "thank": {
    "precision": 1.0,
    "recall": 1.0,
    "f1-score": 1.0,
    "support": 14,
    "confused_with": {}
  },
  "greet": {
    "precision": 1.0,
    "recall": 1.0,
    "f1-score": 1.0,
    "support": 13,
    "confused_with": {}
  },
  "accuracy": 1.0,
  "macro avg": {
    "precision": 1.0,
    "recall": 1.0,
    "f1-score": 1.0,
    "support": 142
  },
  "weighted avg": {
    "precision": 1.0,
    "recall": 1.0,
    "f1-score": 1.0,
    "support": 142
  }
}